{
    "chain": [
        {
            "index": 0,
            "previousHash": "0",
            "timestamp": 1698226371582,
            "data": [],
            "hash": "a7a4c41f58f99604c2b34a4e451567b70343462c3aca09050999f7070858f86e",
            "nonce": 0
        },
        {
            "index": 0,
            "previousHash": "a7a4c41f58f99604c2b34a4e451567b70343462c3aca09050999f7070858f86e",
            "timestamp": 1698226371587,
            "data": [
                {
                    "fromAddress": "address45",
                    "toAddress": "address25",
                    "amount": 118
                }
            ],
            "hash": "00001e9c4c3851b764ba0e7aa82d02e778afa177667e900f60ddc9472034ca4f",
            "nonce": 199980
        },
        {
            "index": 1,
            "previousHash": "00001e9c4c3851b764ba0e7aa82d02e778afa177667e900f60ddc9472034ca4f",
            "timestamp": 1698226372510,
            "data": [
                {
                    "fromAddress": "address53",
                    "toAddress": "address34",
                    "amount": 62
                }
            ],
            "hash": "0000630cb787b6b442ea9714ba150450d4b6ea2836963a0ed00268dc3463f548",
            "nonce": 29390
        },
        {
            "index": 2,
            "previousHash": "0000630cb787b6b442ea9714ba150450d4b6ea2836963a0ed00268dc3463f548",
            "timestamp": 1698226372663,
            "data": [
                {
                    "fromAddress": "address62",
                    "toAddress": "address21",
                    "amount": 581
                },
                {
                    "fromAddress": "address64",
                    "toAddress": "address12",
                    "amount": 761
                },
                {
                    "fromAddress": "address3",
                    "toAddress": "address60",
                    "amount": 709
                }
            ],
            "hash": "0000715a3b63b4458c23ee49bbfc52197c27a6907a1dd793342d1dd2feaf4ea8",
            "nonce": 27585
        },
        {
            "index": 3,
            "previousHash": "0000715a3b63b4458c23ee49bbfc52197c27a6907a1dd793342d1dd2feaf4ea8",
            "timestamp": 1698226372807,
            "data": [
                {
                    "fromAddress": "address4",
                    "toAddress": "address44",
                    "amount": 985
                },
                {
                    "fromAddress": "address81",
                    "toAddress": "address39",
                    "amount": 444
                },
                {
                    "fromAddress": "address61",
                    "toAddress": "address79",
                    "amount": 324
                }
            ],
            "hash": "0000f0a30e45a0dd6d7431ac57602872c166aa518812e5e15db1d956d8b70328",
            "nonce": 34141
        },
        {
            "index": 4,
            "previousHash": "0000f0a30e45a0dd6d7431ac57602872c166aa518812e5e15db1d956d8b70328",
            "timestamp": 1698226372967,
            "data": [
                {
                    "fromAddress": "address44",
                    "toAddress": "address41",
                    "amount": 667
                },
                {
                    "fromAddress": "address92",
                    "toAddress": "address25",
                    "amount": 200
                },
                {
                    "fromAddress": "address15",
                    "toAddress": "address92",
                    "amount": 710
                }
            ],
            "hash": "0000b43552fd4f580658777e753c2ffa1b54e5b4443a4eae7f4321c892e98ca4",
            "nonce": 236427
        },
        {
            "index": 5,
            "previousHash": "0000b43552fd4f580658777e753c2ffa1b54e5b4443a4eae7f4321c892e98ca4",
            "timestamp": 1698226374052,
            "data": [
                {
                    "fromAddress": "address6",
                    "toAddress": "address73",
                    "amount": 614
                },
                {
                    "fromAddress": "address34",
                    "toAddress": "address21",
                    "amount": 379
                },
                {
                    "fromAddress": "address98",
                    "toAddress": "address38",
                    "amount": 739
                },
                {
                    "fromAddress": "address53",
                    "toAddress": "address70",
                    "amount": 497
                }
            ],
            "hash": "0000895bcc3bfc7b6e4f9a234d0d5069e354dc8cb6676b86602dfbcd601bcb2b",
            "nonce": 12308
        },
        {
            "index": 6,
            "previousHash": "0000895bcc3bfc7b6e4f9a234d0d5069e354dc8cb6676b86602dfbcd601bcb2b",
            "timestamp": 1698226374112,
            "data": [
                {
                    "fromAddress": "address42",
                    "toAddress": "address8",
                    "amount": 235
                },
                {
                    "fromAddress": "address8",
                    "toAddress": "address20",
                    "amount": 907
                },
                {
                    "fromAddress": "address82",
                    "toAddress": "address13",
                    "amount": 38
                },
                {
                    "fromAddress": "address97",
                    "toAddress": "address90",
                    "amount": 763
                },
                {
                    "fromAddress": "address57",
                    "toAddress": "address29",
                    "amount": 966
                }
            ],
            "hash": "0000c05968738bc82c159db9f4fe90707be6002392353734be517b312d9659d6",
            "nonce": 22944
        }
    ],
    "difficulty": 4
}